{
  "quick_bite": [
    {
      "name": "Charleys Cheesesteaks",
      "distance": "0.5 mi",
      "url": "https://www.google.com/maps/search/Charleys%20Cheesesteaks+near+33.0774432%2C-117.05942270000001"
    },
    {
      "name": "Panda Express",
      "distance": "0.6 mi",
      "url": "https://www.google.com/maps/search/Panda%20Express+near+33.0774432%2C-117.05942270000001"
    },
    {
      "name": "Snack Time",
      "distance": "0.6 mi",
      "url": "https://www.google.com/maps/search/Snack%20Time+near+33.0774432%2C-117.05942270000001"
    },
    {
      "name": "Chipotle Mexican Grill",
      "distance": "0.6 mi",
      "url": "https://www.google.com/maps/search/Chipotle%20Mexican%20Grill+near+33.0774432%2C-117.05942270000001"
    },
    {
      "name": "Sbarro North County Fair",
      "distance": "0.6 mi",
      "url": "https://www.google.com/maps/search/Sbarro%20North%20County%20Fair+near+33.0774432%2C-117.05942270000001"
    },
    {
      "name": "Potato Corner",
      "distance": "0.6 mi",
      "url": "https://www.google.com/maps/search/Potato%20Corner+near+33.0774432%2C-117.05942270000001"
    },
    {
      "name": "Wetzel's Pretzels",
      "distance": "0.6 mi",
      "url": "https://www.google.com/maps/search/Wetzel's%20Pretzels+near+33.0774432%2C-117.05942270000001"
    }
  ],
  "coffee": [
    {
      "name": "Coast Coffee Co",
      "distance": "0.6 mi",
      "url": "https://www.google.com/maps/search/Coast%20Coffee%20Co+near+33.0774432%2C-117.05942270000001"
    }
  ],
  "team_lunch": [
    {
      "name": "Panini Kabob Grill - Escondido",
      "distance": "0.5 mi",
      "url": "https://www.google.com/maps/search/Panini%20Kabob%20Grill%20-%20Escondido+near+33.0774432%2C-117.05942270000001"
    },
    {
      "name": "Suki Hana Japan",
      "distance": "0.6 mi",
      "url": "https://www.google.com/maps/search/Suki%20Hana%20Japan+near+33.0774432%2C-117.05942270000001"
    },
    {
      "name": "Oggis Pizza & Brewing Co.",
      "distance": "0.6 mi",
      "url": "https://www.google.com/maps/search/Oggis%20Pizza%20%26%20Brewing%20Co.+near+33.0774432%2C-117.05942270000001"
    },
    {
      "name": "Men-ya Mufu - Coming Soon",
      "distance": "0.6 mi",
      "url": "https://www.google.com/maps/search/Men-ya%20Mufu%20-%20Coming%20Soon+near+33.0774432%2C-117.05942270000001"
    },
    {
      "name": "On The Border Mexican Grill & Cantina",
      "distance": "0.6 mi",
      "url": "https://www.google.com/maps/search/On%20The%20Border%20Mexican%20Grill%20%26%20Cantina+near+33.0774432%2C-117.05942270000001"
    }
  ],
  "dinner": [
    {
      "name": "Slurp",
      "distance": "0.5 mi",
      "url": "https://www.google.com/maps/search/Slurp+near+33.0774432%2C-117.05942270000001"
    },
    {
      "name": "Pioneer Organic Cuisine",
      "distance": "0.5 mi",
      "url": "https://www.google.com/maps/search/Pioneer%20Organic%20Cuisine+near+33.0774432%2C-117.05942270000001"
    },
    {
      "name": "Cinnabon",
      "distance": "0.6 mi",
      "url": "https://www.google.com/maps/search/Cinnabon+near+33.0774432%2C-117.05942270000001"
    },
    {
      "name": "Tacos oasis",
      "distance": "0.6 mi",
      "url": "https://www.google.com/maps/search/Tacos%20oasis+near+33.0774432%2C-117.05942270000001"
    }
  ],
  "bowling": [
    {
      "name": "Round1 Bowling & Arcade Escondido - Coming Soon",
      "distance": "0.5 mi",
      "url": "https://www.google.com/maps/search/Round1%20Bowling%20%26%20Arcade%20Escondido%20-%20Coming%20Soon+near+33.0774432%2C-117.05942270000001"
    }
  ],
  "arcade": [],
  "movies": [
    {
      "name": "Regal Cinemas 16",
      "distance": "3.4 mi",
      "url": "https://www.google.com/maps/search/Regal%20Cinemas%2016+near+33.0774432%2C-117.05942270000001",
      "isFar": true
    },
    {
      "name": "Regal Escondido",
      "distance": "3.4 mi",
      "url": "https://www.google.com/maps/search/Regal%20Escondido+near+33.0774432%2C-117.05942270000001",
      "isFar": true
    }
  ],
  "fun": [
    {
      "name": "Let's Play! VR",
      "distance": "0.6 mi",
      "url": "https://www.google.com/maps/search/Let's%20Play!%20VR+near+33.0774432%2C-117.05942270000001"
    },
    {
      "name": "Kyatcha Arcades",
      "distance": "0.6 mi",
      "url": "https://www.google.com/maps/search/Kyatcha%20Arcades+near+33.0774432%2C-117.05942270000001"
    },
    {
      "name": "Monkiddos",
      "distance": "1.5 mi",
      "url": "https://www.google.com/maps/search/Monkiddos+near+33.0774432%2C-117.05942270000001"
    },
    {
      "name": "FUNBOX Bounce & Party Center",
      "distance": "1.9 mi",
      "url": "https://www.google.com/maps/search/FUNBOX%20Bounce%20%26%20Party%20Center+near+33.0774432%2C-117.05942270000001"
    },
    {
      "name": "Cinema Escape Rooms - Main",
      "distance": "3.3 mi",
      "url": "https://www.google.com/maps/search/Cinema%20Escape%20Rooms%20-%20Main+near+33.0774432%2C-117.05942270000001",
      "isFar": true
    },
    {
      "name": "Cinema Escape Rooms at the ArtHatch",
      "distance": "3.3 mi",
      "url": "https://www.google.com/maps/search/Cinema%20Escape%20Rooms%20at%20the%20ArtHatch+near+33.0774432%2C-117.05942270000001",
      "isFar": true
    },
    {
      "name": "The Forsaken Archives Escape Rooms",
      "distance": "4.1 mi",
      "url": "https://www.google.com/maps/search/The%20Forsaken%20Archives%20Escape%20Rooms+near+33.0774432%2C-117.05942270000001",
      "isFar": true
    }
  ],
  "hotels": [
    {
      "name": "Upscale Oasis Retreat Views",
      "distance": "0.3 mi",
      "url": "https://www.google.com/maps/search/Upscale%20Oasis%20Retreat%20Views+near+33.0774432%2C-117.05942270000001"
    },
    {
      "name": "Upscale Oasis Retreat with Views",
      "distance": "0.5 mi",
      "url": "https://www.google.com/maps/search/Upscale%20Oasis%20Retreat%20with%20Views+near+33.0774432%2C-117.05942270000001"
    },
    {
      "name": "Stylish Casita In Escondido",
      "distance": "0.5 mi",
      "url": "https://www.google.com/maps/search/Stylish%20Casita%20In%20Escondido+near+33.0774432%2C-117.05942270000001"
    },
    {
      "name": "Charming, tranquil guesthouse for a relaxing stay",
      "distance": "0.7 mi",
      "url": "https://www.google.com/maps/search/Charming%2C%20tranquil%20guesthouse%20for%20a%20relaxing%20stay+near+33.0774432%2C-117.05942270000001"
    },
    {
      "name": "Lovely spacious apartment perfect for exploring San Diego",
      "distance": "0.7 mi",
      "url": "https://www.google.com/maps/search/Lovely%20spacious%20apartment%20perfect%20for%20exploring%20San%20Diego+near+33.0774432%2C-117.05942270000001"
    },
    {
      "name": "Beautiful New Home with Large Balcony Views!",
      "distance": "0.8 mi",
      "url": "https://www.google.com/maps/search/Beautiful%20New%20Home%20with%20Large%20Balcony%20Views!+near+33.0774432%2C-117.05942270000001"
    },
    {
      "name": "Beautiful New Home with Large Balcony & Views!",
      "distance": "0.8 mi",
      "url": "https://www.google.com/maps/search/Beautiful%20New%20Home%20with%20Large%20Balcony%20%26%20Views!+near+33.0774432%2C-117.05942270000001"
    }
  ],
  "gas": [
    {
      "name": "Chevron",
      "distance": "0.8 mi",
      "url": "https://www.google.com/maps/search/Chevron+near+33.0774432%2C-117.05942270000001"
    },
    {
      "name": "Shell",
      "distance": "0.8 mi",
      "url": "https://www.google.com/maps/search/Shell+near+33.0774432%2C-117.05942270000001"
    },
    {
      "name": "Shell",
      "distance": "0.8 mi",
      "url": "https://www.google.com/maps/search/Shell+near+33.0774432%2C-117.05942270000001"
    },
    {
      "name": "DANIEL AND MATTHEW AMP",
      "distance": "1.3 mi",
      "url": "https://www.google.com/maps/search/DANIEL%20AND%20MATTHEW%20AMP+near+33.0774432%2C-117.05942270000001"
    },
    {
      "name": "Varso Gas Station",
      "distance": "1.3 mi",
      "url": "https://www.google.com/maps/search/Varso%20Gas%20Station+near+33.0774432%2C-117.05942270000001"
    }
  ]
}