{
  "quick_bite": [
    {
      "name": "Subway (South Medford)",
      "distance": "0.1 mi",
      "url": "https://www.google.com/maps/search/Subway%20(South%20Medford)+near+42.3111719%2C-122.85304649999999"
    },
    {
      "name": "MOD Pizza",
      "distance": "0.1 mi",
      "url": "https://www.google.com/maps/search/MOD%20Pizza+near+42.3111719%2C-122.85304649999999"
    },
    {
      "name": "Chipotle Mexican Grill",
      "distance": "0.2 mi",
      "url": "https://www.google.com/maps/search/Chipotle%20Mexican%20Grill+near+42.3111719%2C-122.85304649999999"
    },
    {
      "name": "Panda Express",
      "distance": "0.2 mi",
      "url": "https://www.google.com/maps/search/Panda%20Express+near+42.3111719%2C-122.85304649999999"
    },
    {
      "name": "Five Guys",
      "distance": "0.2 mi",
      "url": "https://www.google.com/maps/search/Five%20Guys+near+42.3111719%2C-122.85304649999999"
    },
    {
      "name": "Jersey Mike's Subs",
      "distance": "0.2 mi",
      "url": "https://www.google.com/maps/search/Jersey%20Mike's%20Subs+near+42.3111719%2C-122.85304649999999"
    },
    {
      "name": "Taco Bell",
      "distance": "0.2 mi",
      "url": "https://www.google.com/maps/search/Taco%20Bell+near+42.3111719%2C-122.85304649999999"
    }
  ],
  "coffee": [
    {
      "name": "Artisan Bakery Cafe",
      "distance": "0.1 mi",
      "url": "https://www.google.com/maps/search/Artisan%20Bakery%20Cafe+near+42.3111719%2C-122.85304649999999"
    },
    {
      "name": "Starbucks Coffee Company",
      "distance": "0.2 mi",
      "url": "https://www.google.com/maps/search/Starbucks%20Coffee%20Company+near+42.3111719%2C-122.85304649999999"
    }
  ],
  "team_lunch": [
    {
      "name": "International House of Pancakes",
      "distance": "0.1 mi",
      "url": "https://www.google.com/maps/search/International%20House%20of%20Pancakes+near+42.3111719%2C-122.85304649999999"
    },
    {
      "name": "Pardon My Cheesesteak",
      "distance": "0.1 mi",
      "url": "https://www.google.com/maps/search/Pardon%20My%20Cheesesteak+near+42.3111719%2C-122.85304649999999"
    },
    {
      "name": "IHOP",
      "distance": "0.1 mi",
      "url": "https://www.google.com/maps/search/IHOP+near+42.3111719%2C-122.85304649999999"
    },
    {
      "name": "KFC",
      "distance": "0.2 mi",
      "url": "https://www.google.com/maps/search/KFC+near+42.3111719%2C-122.85304649999999"
    },
    {
      "name": "Seasons Chilaquiles",
      "distance": "0.3 mi",
      "url": "https://www.google.com/maps/search/Seasons%20Chilaquiles+near+42.3111719%2C-122.85304649999999"
    }
  ],
  "dinner": [
    {
      "name": "Las Margaritas Bar & Grill",
      "distance": "0.1 mi",
      "url": "https://www.google.com/maps/search/Las%20Margaritas%20Bar%20%26%20Grill+near+42.3111719%2C-122.85304649999999"
    },
    {
      "name": "Dave's Hot Chicken",
      "distance": "0.1 mi",
      "url": "https://www.google.com/maps/search/Dave's%20Hot%20Chicken+near+42.3111719%2C-122.85304649999999"
    },
    {
      "name": "The Point Pub and Grill",
      "distance": "0.1 mi",
      "url": "https://www.google.com/maps/search/The%20Point%20Pub%20and%20Grill+near+42.3111719%2C-122.85304649999999"
    },
    {
      "name": "Rooted: South Medford",
      "distance": "0.1 mi",
      "url": "https://www.google.com/maps/search/Rooted%3A%20South%20Medford+near+42.3111719%2C-122.85304649999999"
    },
    {
      "name": "Walmart Bakery",
      "distance": "0.2 mi",
      "url": "https://www.google.com/maps/search/Walmart%20Bakery+near+42.3111719%2C-122.85304649999999"
    }
  ],
  "bowling": [
    {
      "name": "Lava Lanes of Medford",
      "distance": "3.3 mi",
      "url": "https://www.google.com/maps/search/Lava%20Lanes%20of%20Medford+near+42.3111719%2C-122.85304649999999",
      "isFar": true
    }
  ],
  "arcade": [],
  "movies": [],
  "fun": [
    {
      "name": "Fichtner-Mainwaring Park Splash Pad",
      "distance": "0.8 mi",
      "url": "https://www.google.com/maps/search/Fichtner-Mainwaring%20Park%20Splash%20Pad+near+42.3111719%2C-122.85304649999999"
    },
    {
      "name": "Stumpt! Escape Games",
      "distance": "0.8 mi",
      "url": "https://www.google.com/maps/search/Stumpt!%20Escape%20Games+near+42.3111719%2C-122.85304649999999"
    },
    {
      "name": "Get Air Trampoline Park",
      "distance": "1.7 mi",
      "url": "https://www.google.com/maps/search/Get%20Air%20Trampoline%20Park+near+42.3111719%2C-122.85304649999999"
    },
    {
      "name": "Baffled Escape Rooms",
      "distance": "2.5 mi",
      "url": "https://www.google.com/maps/search/Baffled%20Escape%20Rooms+near+42.3111719%2C-122.85304649999999"
    },
    {
      "name": "Howard Park Splash Pad",
      "distance": "3.8 mi",
      "url": "https://www.google.com/maps/search/Howard%20Park%20Splash%20Pad+near+42.3111719%2C-122.85304649999999",
      "isFar": true
    }
  ],
  "hotels": [
    {
      "name": "Holiday Inn Express & Suites Medford by IHG",
      "distance": "0.1 mi",
      "url": "https://www.google.com/maps/search/Holiday%20Inn%20Express%20%26%20Suites%20Medford%20by%20IHG+near+42.3111719%2C-122.85304649999999"
    },
    {
      "name": "SpringHill Suites by Marriott Medford",
      "distance": "0.1 mi",
      "url": "https://www.google.com/maps/search/SpringHill%20Suites%20by%20Marriott%20Medford+near+42.3111719%2C-122.85304649999999"
    },
    {
      "name": "TownePlace Suites by Marriott Medford",
      "distance": "0.1 mi",
      "url": "https://www.google.com/maps/search/TownePlace%20Suites%20by%20Marriott%20Medford+near+42.3111719%2C-122.85304649999999"
    },
    {
      "name": "Fairfield by Marriott Inn & Suites Medford",
      "distance": "0.2 mi",
      "url": "https://www.google.com/maps/search/Fairfield%20by%20Marriott%20Inn%20%26%20Suites%20Medford+near+42.3111719%2C-122.85304649999999"
    },
    {
      "name": "Clarion Pointe Medford",
      "distance": "0.3 mi",
      "url": "https://www.google.com/maps/search/Clarion%20Pointe%20Medford+near+42.3111719%2C-122.85304649999999"
    },
    {
      "name": "Comfort Inn Medford South",
      "distance": "0.3 mi",
      "url": "https://www.google.com/maps/search/Comfort%20Inn%20Medford%20South+near+42.3111719%2C-122.85304649999999"
    },
    {
      "name": "Best Western Horizon Inn",
      "distance": "0.3 mi",
      "url": "https://www.google.com/maps/search/Best%20Western%20Horizon%20Inn+near+42.3111719%2C-122.85304649999999"
    }
  ],
  "gas": [
    {
      "name": "Shell",
      "distance": "0.2 mi",
      "url": "https://www.google.com/maps/search/Shell+near+42.3111719%2C-122.85304649999999"
    },
    {
      "name": "Family Mart",
      "distance": "0.2 mi",
      "url": "https://www.google.com/maps/search/Family%20Mart+near+42.3111719%2C-122.85304649999999"
    },
    {
      "name": "Fred Meyer Fuel Center",
      "distance": "0.3 mi",
      "url": "https://www.google.com/maps/search/Fred%20Meyer%20Fuel%20Center+near+42.3111719%2C-122.85304649999999"
    },
    {
      "name": "Kroger Fuel",
      "distance": "0.3 mi",
      "url": "https://www.google.com/maps/search/Kroger%20Fuel+near+42.3111719%2C-122.85304649999999"
    },
    {
      "name": "Chevron Medford",
      "distance": "0.4 mi",
      "url": "https://www.google.com/maps/search/Chevron%20Medford+near+42.3111719%2C-122.85304649999999"
    }
  ]
}