{
  "quick_bite": [
    {
      "name": "Subway",
      "distance": "0.5 mi",
      "url": "https://www.google.com/maps/search/Subway+near+44.042815%2C-123.10855099999999"
    },
    {
      "name": "Burrito Boy",
      "distance": "0.5 mi",
      "url": "https://www.google.com/maps/search/Burrito%20Boy+near+44.042815%2C-123.10855099999999"
    },
    {
      "name": "Hot Mama's Wings",
      "distance": "0.5 mi",
      "url": "https://www.google.com/maps/search/Hot%20Mama's%20Wings+near+44.042815%2C-123.10855099999999"
    },
    {
      "name": "Wonder Wok Restaurant and Bar",
      "distance": "0.6 mi",
      "url": "https://www.google.com/maps/search/Wonder%20Wok%20Restaurant%20and%20Bar+near+44.042815%2C-123.10855099999999"
    },
    {
      "name": "Albee's N.Y. Gyros",
      "distance": "0.6 mi",
      "url": "https://www.google.com/maps/search/Albee's%20N.Y.%20Gyros+near+44.042815%2C-123.10855099999999"
    }
  ],
  "coffee": [
    {
      "name": "Starbucks Coffee Company",
      "distance": "0.4 mi",
      "url": "https://www.google.com/maps/search/Starbucks%20Coffee%20Company+near+44.042815%2C-123.10855099999999"
    },
    {
      "name": "Mi Cafe +",
      "distance": "0.6 mi",
      "url": "https://www.google.com/maps/search/Mi%20Cafe%20%2B+near+44.042815%2C-123.10855099999999"
    },
    {
      "name": "Dutch Bros Coffee",
      "distance": "0.6 mi",
      "url": "https://www.google.com/maps/search/Dutch%20Bros%20Coffee+near+44.042815%2C-123.10855099999999"
    }
  ],
  "team_lunch": [
    {
      "name": "Hey, Neighbor! - Friendly",
      "distance": "0.4 mi",
      "url": "https://www.google.com/maps/search/Hey%2C%20Neighbor!%20-%20Friendly+near+44.042815%2C-123.10855099999999"
    }
  ],
  "dinner": [
    {
      "name": "Chambers Grill and Taphouse",
      "distance": "0.4 mi",
      "url": "https://www.google.com/maps/search/Chambers%20Grill%20and%20Taphouse+near+44.042815%2C-123.10855099999999"
    },
    {
      "name": "Angkor Cafe",
      "distance": "0.5 mi",
      "url": "https://www.google.com/maps/search/Angkor%20Cafe+near+44.042815%2C-123.10855099999999"
    },
    {
      "name": "Cafe Soriah",
      "distance": "0.5 mi",
      "url": "https://www.google.com/maps/search/Cafe%20Soriah+near+44.042815%2C-123.10855099999999"
    },
    {
      "name": "Grab'Wich",
      "distance": "0.5 mi",
      "url": "https://www.google.com/maps/search/Grab'Wich+near+44.042815%2C-123.10855099999999"
    },
    {
      "name": "Fresh And Natural Mexican Eatery",
      "distance": "0.6 mi",
      "url": "https://www.google.com/maps/search/Fresh%20And%20Natural%20Mexican%20Eatery+near+44.042815%2C-123.10855099999999"
    },
    {
      "name": "The Coco Nut",
      "distance": "0.6 mi",
      "url": "https://www.google.com/maps/search/The%20Coco%20Nut+near+44.042815%2C-123.10855099999999"
    }
  ],
  "bowling": [
    {
      "name": "Round1 Bowling & Arcade Valley River Center",
      "distance": "1.8 mi",
      "url": "https://www.google.com/maps/search/Round1%20Bowling%20%26%20Arcade%20Valley%20River%20Center+near+44.042815%2C-123.10855099999999"
    },
    {
      "name": "Emerald Lanes",
      "distance": "2.0 mi",
      "url": "https://www.google.com/maps/search/Emerald%20Lanes+near+44.042815%2C-123.10855099999999"
    },
    {
      "name": "Lane 25",
      "distance": "2.9 mi",
      "url": "https://www.google.com/maps/search/Lane%2025+near+44.042815%2C-123.10855099999999"
    }
  ],
  "arcade": [],
  "movies": [
    {
      "name": "Metro Cinemas",
      "distance": "0.9 mi",
      "url": "https://www.google.com/maps/search/Metro%20Cinemas+near+44.042815%2C-123.10855099999999"
    },
    {
      "name": "Art House",
      "distance": "1.2 mi",
      "url": "https://www.google.com/maps/search/Art%20House+near+44.042815%2C-123.10855099999999"
    },
    {
      "name": "Regal 15 Cinemas Imax",
      "distance": "1.7 mi",
      "url": "https://www.google.com/maps/search/Regal%2015%20Cinemas%20Imax+near+44.042815%2C-123.10855099999999"
    }
  ],
  "fun": [
    {
      "name": "Trapdoor Escape Rooms",
      "distance": "1.0 mi",
      "url": "https://www.google.com/maps/search/Trapdoor%20Escape%20Rooms+near+44.042815%2C-123.10855099999999"
    },
    {
      "name": "Putters Family Entertainment Center",
      "distance": "2.8 mi",
      "url": "https://www.google.com/maps/search/Putters%20Family%20Entertainment%20Center+near+44.042815%2C-123.10855099999999"
    },
    {
      "name": "Get Air Trampoline Park",
      "distance": "2.9 mi",
      "url": "https://www.google.com/maps/search/Get%20Air%20Trampoline%20Park+near+44.042815%2C-123.10855099999999"
    },
    {
      "name": "DEFY Eugene",
      "distance": "4.0 mi",
      "url": "https://www.google.com/maps/search/DEFY%20Eugene+near+44.042815%2C-123.10855099999999",
      "isFar": true
    }
  ],
  "hotels": [
    {
      "name": "A place to go to get away.",
      "distance": "0.2 mi",
      "url": "https://www.google.com/maps/search/A%20place%20to%20go%20to%20get%20away.+near+44.042815%2C-123.10855099999999"
    },
    {
      "name": "The Mellow Yellow: 2.2 mi to UO/ 3.5 mi to Autzen",
      "distance": "0.2 mi",
      "url": "https://www.google.com/maps/search/The%20Mellow%20Yellow%3A%202.2%20mi%20to%20UO%2F%203.5%20mi%20to%20Autzen+near+44.042815%2C-123.10855099999999"
    },
    {
      "name": "The Sunflower Studio:2.2 mi to UO/3.5 mi to Autzen",
      "distance": "0.2 mi",
      "url": "https://www.google.com/maps/search/The%20Sunflower%20Studio%3A2.2%20mi%20to%20UO%2F3.5%20mi%20to%20Autzen+near+44.042815%2C-123.10855099999999"
    },
    {
      "name": "The Sunflower Studio:2.2 mi to UO /3.5 mi to Autzen",
      "distance": "0.2 mi",
      "url": "https://www.google.com/maps/search/The%20Sunflower%20Studio%3A2.2%20mi%20to%20UO%20%2F3.5%20mi%20to%20Autzen+near+44.042815%2C-123.10855099999999"
    },
    {
      "name": "The Mellow Yellow: 2.2 mi to UO / 3.5 mi to Autzen",
      "distance": "0.2 mi",
      "url": "https://www.google.com/maps/search/The%20Mellow%20Yellow%3A%202.2%20mi%20to%20UO%20%2F%203.5%20mi%20to%20Autzen+near+44.042815%2C-123.10855099999999"
    },
    {
      "name": "Art Alley Studio- Downtown Eugene",
      "distance": "0.3 mi",
      "url": "https://www.google.com/maps/search/Art%20Alley%20Studio-%20Downtown%20Eugene+near+44.042815%2C-123.10855099999999"
    }
  ],
  "gas": [
    {
      "name": "76",
      "distance": "0.5 mi",
      "url": "https://www.google.com/maps/search/76+near+44.042815%2C-123.10855099999999"
    },
    {
      "name": "BUY2 FUEL",
      "distance": "0.5 mi",
      "url": "https://www.google.com/maps/search/BUY2%20FUEL+near+44.042815%2C-123.10855099999999"
    },
    {
      "name": "Shell",
      "distance": "0.6 mi",
      "url": "https://www.google.com/maps/search/Shell+near+44.042815%2C-123.10855099999999"
    },
    {
      "name": "Astro Gas 207",
      "distance": "0.7 mi",
      "url": "https://www.google.com/maps/search/Astro%20Gas%20207+near+44.042815%2C-123.10855099999999"
    }
  ]
}
