{
  "quick_bite": [
    {
      "name": "Wawa",
      "distance": "0.2 mi",
      "url": "https://www.google.com/maps/search/?api=1&query=Wawa&query_place_id=ChIJIyibKoNLwYkR3C4hqCEQlT0&center=40.0356185,-74.9228997"
    },
    {
      "name": "Arby's",
      "distance": "0.5 mi",
      "url": "https://www.google.com/maps/search/?api=1&query=Arby's&query_place_id=ChIJpRlhZINLwYkR39tD_a58zkY&center=40.038020599999996,-74.91581599999999"
    },
    {
      "name": "KFC",
      "distance": "0.5 mi",
      "url": "https://www.google.com/maps/search/?api=1&query=KFC&query_place_id=ChIJPWpqgYRLwYkR_VcGS90_9V4&center=40.0388168,-74.9145197"
    },
    {
      "name": "Mr. Cheesesteak & Pizza of Penny Packer",
      "distance": "1.1 mi",
      "url": "https://www.google.com/maps/search/?api=1&query=Mr.%20Cheesesteak%20%26%20Pizza%20of%20Penny%20Packer&query_place_id=ChIJVVVVVeVLwYkRXe_FqNMFQH8&center=40.042508999999995,-74.9049836"
    },
    {
      "name": "Dunkin'",
      "distance": "1.2 mi",
      "url": "https://www.google.com/maps/search/?api=1&query=Dunkin'&query_place_id=ChIJawmpsZdLwYkROld6CZS7ICs&center=40.027265899999996,-74.9072644"
    },
    {
      "name": "Chick-fil-A",
      "distance": "1.6 mi",
      "url": "https://www.google.com/maps/search/?api=1&query=Chick-fil-A&query_place_id=ChIJAxJYfhhLwYkRDTKjoH2rtts&center=40.0204093,-74.94398190000001"
    }
  ],
  "coffee": [
    {
      "name": "Dunkin'",
      "distance": "1.2 mi",
      "url": "https://www.google.com/maps/search/?api=1&query=Dunkin'&query_place_id=ChIJawmpsZdLwYkROld6CZS7ICs&center=40.027265899999996,-74.9072644"
    },
    {
      "name": "Delran Bagel Cafe",
      "distance": "1.7 mi",
      "url": "https://www.google.com/maps/search/?api=1&query=Delran%20Bagel%20Cafe&query_place_id=ChIJ947xeCJLwYkR53kMRrFHqdQ&center=40.016923999999996,-74.9437265"
    }
  ],
  "team_lunch": [
    {
      "name": "Supremos",
      "distance": "0.4 mi",
      "url": "https://www.google.com/maps/search/?api=1&query=Supremos&query_place_id=ChIJC7cKZoNLwYkRarYJScXZxZI&center=40.037274000000004,-74.917028"
    },
    {
      "name": "NO. 1 Chinese Restaurant",
      "distance": "1.1 mi",
      "url": "https://www.google.com/maps/search/?api=1&query=NO.%201%20Chinese%20Restaurant&query_place_id=ChIJawmpsZdLwYkRBF-lpfxCiUY&center=40.0272055,-74.9081805"
    }
  ],
  "dinner": [
    {
      "name": "Crystal Diner",
      "distance": "0.4 mi",
      "url": "https://www.google.com/maps/search/?api=1&query=Crystal%20Diner&query_place_id=ChIJxcOiPYNLwYkRyS-kneILLC4&center=40.038503399999996,-74.9166983"
    },
    {
      "name": "Best of the Wurst German Kitchen",
      "distance": "1.1 mi",
      "url": "https://www.google.com/maps/search/?api=1&query=Best%20of%20the%20Wurst%20German%20Kitchen&query_place_id=ChIJSeAK7EJLwYkRqEs4zmX7PMA&center=40.0399244,-74.9449891"
    },
    {
      "name": "Kral Mediterranean Restaurant",
      "distance": "1.1 mi",
      "url": "https://www.google.com/maps/search/?api=1&query=Kral%20Mediterranean%20Restaurant&query_place_id=ChIJKXr5FABLwYkR98G6HmOqdyg&center=40.042468199999995,-74.9049604"
    },
    {
      "name": "Ignite cuisine",
      "distance": "1.1 mi",
      "url": "https://www.google.com/maps/search/?api=1&query=Ignite%20cuisine&query_place_id=ChIJY0QHzHdLwYkRBE91ijHNwuk&center=40.0272029,-74.908098"
    },
    {
      "name": "Guilli's Authentic Mexican Cuisine",
      "distance": "1.1 mi",
      "url": "https://www.google.com/maps/search/?api=1&query=Guilli's%20Authentic%20Mexican%20Cuisine&query_place_id=ChIJa8juz5dLwYkRAtM-YfxdEvw&center=40.026634099999995,-74.90852559999999"
    }
  ],
  "bowling": [
    {
      "name": "Bowlero Bristol",
      "distance": "4.7 mi",
      "url": "https://www.google.com/maps/search/?api=1&query=Bowlero%20Bristol&query_place_id=ChIJj7ylQdtNwYkR97nCup5g-Vo&center=40.0977738,-74.88443339999999",
      "isFar": true
    }
  ],
  "arcade": [],
  "movies": [
    {
      "name": "AMC Woodhaven 10",
      "distance": "3.4 mi",
      "url": "https://www.google.com/maps/search/?api=1&query=AMC%20Woodhaven%2010&query_place_id=ChIJde7TDrVMwYkRF5Ok6l_BdRU&center=40.0743448,-74.96782569999999",
      "isFar": true
    }
  ],
  "fun": [
    {
      "name": "MLB baseball mud",
      "distance": "0.7 mi",
      "url": "https://www.google.com/maps/search/?api=1&query=MLB%20baseball%20mud&query_place_id=ChIJxXOEFgBLwYkRpnNT_5IOOKQ&center=40.0276717,-74.9283329"
    },
    {
      "name": "Exit 4 Escape Rooms",
      "distance": "1.8 mi",
      "url": "https://www.google.com/maps/search/?api=1&query=Exit%204%20Escape%20Rooms&query_place_id=ChIJm9t1w0VLwYkRutJuQOpqWhs&center=40.016763,-74.94399279999999"
    },
    {
      "name": "TakeOff Adenture Park",
      "distance": "1.9 mi",
      "url": "https://www.google.com/maps/search/?api=1&query=TakeOff%20Adenture%20Park&query_place_id=ChIJ10qussBNwYkRfWUToTUbcJg&center=40.0541957,-74.8961352"
    },
    {
      "name": "Funzilla Delran",
      "distance": "2.0 mi",
      "url": "https://www.google.com/maps/search/?api=1&query=Funzilla%20Delran&query_place_id=ChIJy-Lw_ytLwYkRAWfnjc2WaZA&center=40.0179709,-74.9536427"
    }
  ],
  "hotels": [
    {
      "name": "Beverly Courts Motel",
      "distance": "1.1 mi",
      "url": "https://www.google.com/maps/search/?api=1&query=Beverly%20Courts%20Motel&query_place_id=ChIJcQ0oy4lLwYkRJcAkl6B5EVY&center=40.0441667,-74.90611109999999"
    },
    {
      "name": "Nightmare on 2nd Street",
      "distance": "1.7 mi",
      "url": "https://www.google.com/maps/search/?api=1&query=Nightmare%20on%202nd%20Street&query_place_id=ChIJTeoaI6JMwYkR7A9JcFZBMvQ&center=40.0566263,-74.9459356"
    },
    {
      "name": "Edgewater Park Lights",
      "distance": "1.8 mi",
      "url": "https://www.google.com/maps/search/?api=1&query=Edgewater%20Park%20Lights&query_place_id=ChIJ7zV9EqdNwYkRMHm5522a3K4&center=40.0570046,-74.90256289999999"
    }
  ],
  "gas": [
    {
      "name": "Exxon",
      "distance": "0.5 mi",
      "url": "https://www.google.com/maps/search/Exxon+near+40.0373492%2C-74.92472049999999"
    },
    {
      "name": "Sunoco",
      "distance": "1.0 mi",
      "url": "https://www.google.com/maps/search/Sunoco+near+40.0373492%2C-74.92472049999999"
    },
    {
      "name": "Citgo",
      "distance": "1.3 mi",
      "url": "https://www.google.com/maps/search/Citgo+near+40.0373492%2C-74.92472049999999"
    },
    {
      "name": "Gulf",
      "distance": "1.3 mi",
      "url": "https://www.google.com/maps/search/Gulf+near+40.0373492%2C-74.92472049999999"
    }
  ]
}
