{
  "quick_bite": [
    {
      "name": "Taco John's",
      "distance": "0.4 mi",
      "url": "https://www.google.com/maps/search/Taco%20John's+near+41.8429718%2C-103.6571807"
    },
    {
      "name": "MANUEL CANDY SHOP",
      "distance": "1.1 mi",
      "url": "https://www.google.com/maps/search/MANUEL%20CANDY%20SHOP+near+41.8429718%2C-103.6571807"
    },
    {
      "name": "Classic Lanes/ Lane 17 Pro Shop",
      "distance": "2.0 mi",
      "url": "https://www.google.com/maps/search/Classic%20Lanes%2F%20Lane%2017%20Pro%20Shop+near+41.8429718%2C-103.6571807"
    }
  ],
  "coffee": [
    {
      "name": "Finishline Cafe",
      "distance": "0.4 mi",
      "url": "https://www.google.com/maps/search/Finishline%20Cafe+near+41.8429718%2C-103.6571807"
    },
    {
      "name": "Starbucks Coffee Company",
      "distance": "0.8 mi",
      "url": "https://www.google.com/maps/search/Starbucks%20Coffee%20Company+near+41.8429718%2C-103.6571807"
    },
    {
      "name": "Emporium Express at Main Street Market",
      "distance": "0.9 mi",
      "url": "https://www.google.com/maps/search/Emporium%20Express%20at%20Main%20Street%20Market+near+41.8429718%2C-103.6571807"
    }
  ],
  "team_lunch": [
    {
      "name": "Hot Stuff Pizza",
      "distance": "0.3 mi",
      "url": "https://www.google.com/maps/search/Hot%20Stuff%20Pizza+near+41.8429718%2C-103.6571807"
    }
  ],
  "dinner": [
    {
      "name": "Rise and Shine",
      "distance": "0.2 mi",
      "url": "https://www.google.com/maps/search/Rise%20and%20Shine+near+41.8429718%2C-103.6571807"
    },
    {
      "name": "Sandy's Burritos",
      "distance": "0.2 mi",
      "url": "https://www.google.com/maps/search/Sandy's%20Burritos+near+41.8429718%2C-103.6571807"
    },
    {
      "name": "Steel Grill Restaurant & Bar",
      "distance": "0.2 mi",
      "url": "https://www.google.com/maps/search/Steel%20Grill%20Restaurant%20%26%20Bar+near+41.8429718%2C-103.6571807"
    },
    {
      "name": "Asian Buffet",
      "distance": "0.3 mi",
      "url": "https://www.google.com/maps/search/Asian%20Buffet+near+41.8429718%2C-103.6571807"
    },
    {
      "name": "El Torito Grill",
      "distance": "0.4 mi",
      "url": "https://www.google.com/maps/search/El%20Torito%20Grill+near+41.8429718%2C-103.6571807"
    },
    {
      "name": "Memaw's Barnyard Cafe",
      "distance": "0.6 mi",
      "url": "https://www.google.com/maps/search/Memaw's%20Barnyard%20Cafe+near+41.8429718%2C-103.6571807"
    }
  ],
  "bowling": [],
  "arcade": [],
  "movies": [
    {
      "name": "Midwest Theater",
      "distance": "1.5 mi",
      "url": "https://www.google.com/maps/search/Midwest%20Theater+near+41.8429718%2C-103.6571807"
    },
    {
      "name": "Golden Ticket Cinemas Reel Lux 6",
      "distance": "1.9 mi",
      "url": "https://www.google.com/maps/search/Golden%20Ticket%20Cinemas%20Reel%20Lux%206+near+41.8429718%2C-103.6571807"
    }
  ],
  "fun": [
    {
      "name": "Planet Bounce Mobile",
      "distance": "2.0 mi",
      "url": "https://www.google.com/maps/search/Planet%20Bounce%20Mobile+near+41.8429718%2C-103.6571807"
    }
  ],
  "hotels": [
    {
      "name": "Hotel 21 & Co.",
      "distance": "0.4 mi",
      "url": "https://www.google.com/maps/search/Hotel%2021%20%26%20Co.+near+41.8429718%2C-103.6571807"
    },
    {
      "name": "Arcadia Hotel",
      "distance": "0.4 mi",
      "url": "https://www.google.com/maps/search/Arcadia%20Hotel+near+41.8429718%2C-103.6571807"
    },
    {
      "name": "Blue Bird Mobile Homes Inc",
      "distance": "1.1 mi",
      "url": "https://www.google.com/maps/search/Blue%20Bird%20Mobile%20Homes%20Inc+near+41.8429718%2C-103.6571807"
    }
  ],
  "gas": [
    {
      "name": "Kotaco",
      "distance": "0.2 mi",
      "url": "https://www.google.com/maps/search/Kotaco+near+41.8429718%2C-103.6571807"
    },
    {
      "name": "Sinclair",
      "distance": "0.2 mi",
      "url": "https://www.google.com/maps/search/Sinclair+near+41.8429718%2C-103.6571807"
    },
    {
      "name": "Shell",
      "distance": "0.3 mi",
      "url": "https://www.google.com/maps/search/Shell+near+41.8429718%2C-103.6571807"
    },
    {
      "name": "TEXACO",
      "distance": "0.4 mi",
      "url": "https://www.google.com/maps/search/TEXACO+near+41.8429718%2C-103.6571807"
    }
  ]
}
